<?xml version="1.0" encoding="UTF-8"?>
<database defaultPhpNamingMethod="underscore" heavyIndexing="false" name="iso" package="lib.model.iso" defaultIdMethod="native" noXsd="true"><table skipSql="false" abstract="false" name="web_policy_detail" idMethod="native"><column lazyLoad="false" name="id" type="INTEGER" required="true" autoIncrement="true" primaryKey="true"/><column primaryKey="false" autoIncrement="false" lazyLoad="false" name="content" type="LONGVARCHAR" required="true"/><column primaryKey="false" required="false" autoIncrement="false" lazyLoad="false" name="web_policy_header_id" type="INTEGER"/><column primaryKey="false" autoIncrement="false" lazyLoad="false" name="index_no" type="INTEGER" required="true" default="null"/><column primaryKey="false" required="false" autoIncrement="false" lazyLoad="false" name="date_created" type="TIMESTAMP"/><column primaryKey="false" required="false" autoIncrement="false" lazyLoad="false" name="created_by" type="VARCHAR" size="45"/><column primaryKey="false" required="false" autoIncrement="false" lazyLoad="false" name="date_modified" type="TIMESTAMP"/><column primaryKey="false" required="false" autoIncrement="false" lazyLoad="false" name="modified_by" type="VARCHAR" size="45"/></table><table skipSql="false" abstract="false" name="web_policy_header" idMethod="native"><column lazyLoad="false" name="id" type="INTEGER" required="true" autoIncrement="true" primaryKey="true"/><column primaryKey="false" autoIncrement="false" lazyLoad="false" name="name" type="VARCHAR" size="100" required="true" default="null"/><column primaryKey="false" autoIncrement="false" lazyLoad="false" name="index_no" type="INTEGER" required="true" default="null"/><column primaryKey="false" required="false" autoIncrement="false" lazyLoad="false" name="date_created" type="TIMESTAMP"/><column primaryKey="false" required="false" autoIncrement="false" lazyLoad="false" name="created_by" type="VARCHAR" size="45"/><column primaryKey="false" required="false" autoIncrement="false" lazyLoad="false" name="date_modified" type="TIMESTAMP"/><column primaryKey="false" required="false" autoIncrement="false" lazyLoad="false" name="modified_by" type="VARCHAR" size="45"/></table></database>
